openrelik_worker_common/__init__.py
openrelik_worker_common/archive_utils.py
openrelik_worker_common/debug_utils.py
openrelik_worker_common/file_utils.py
openrelik_worker_common/reporting.py
openrelik_worker_common/task_utils.py
openrelik_worker_common-2024.11.27.dist-info/LICENSE
openrelik_worker_common-2024.11.27.dist-info/METADATA
openrelik_worker_common-2024.11.27.dist-info/WHEEL
openrelik_worker_common-2024.11.27.dist-info/RECORD
