Metadata-Version: 2.1
Name: openrelik-worker-common
Version: 2024.11.27
Summary: Common utilities for OpenRelik workers
Author: Johan Berggren
Author-email: jberggren@gmail.com
Requires-Python: >=3.10,<4.0
Classifier: Programming Language :: Python :: 3
Classifier: Programming Language :: Python :: 3.10
Classifier: Programming Language :: Python :: 3.11
Classifier: Programming Language :: Python :: 3.12
Requires-Dist: debugpy (>=1.8.6,<2.0.0)
